asyncio_channel/__init__.py
asyncio_channel/_buffer.py
asyncio_channel/_channel.py
asyncio_channel/_complete_one.py
asyncio_channel/_create_channel.py
asyncio_channel/_create_mix.py
asyncio_channel/_create_multiple.py
asyncio_channel/_create_publication.py
asyncio_channel/_dropping_queue.py
asyncio_channel/_iter.py
asyncio_channel/_map.py
asyncio_channel/_merge.py
asyncio_channel/_mixin.py
asyncio_channel/_onto_channel.py
asyncio_channel/_pipe.py
asyncio_channel/_reduce.py
asyncio_channel/_shield.py
asyncio_channel/_sliding_queue.py
asyncio_channel/_split.py
asyncio_channel/_util.py
asyncio_channel-0.9.1.dist-info/LICENSE
asyncio_channel-0.9.1.dist-info/WHEEL
asyncio_channel-0.9.1.dist-info/METADATA
asyncio_channel-0.9.1.dist-info/RECORD
