Metadata-Version: 2.1
Name: asyncio-channel
Version: 0.9.1
Summary: Asynchronous channels and utilities.
Home-page: https://github.com/ebb29c/asyncio-channel
License: UNKNOWN
Author: ebb29c
Author-email: 
Requires-Python: ~=3.7
Classifier: Development Status :: 4 - Beta
Classifier: Framework :: AsyncIO
Classifier: Intended Audience :: Developers
Classifier: License :: OSI Approved :: MIT License
Classifier: Programming Language :: Python
Classifier: Programming Language :: Python :: 3
Classifier: Programming Language :: Python :: 3.7
Classifier: Programming Language :: Python :: 3.8
Classifier: Programming Language :: Python :: 3.9
Classifier: Programming Language :: Python :: Implementation :: CPython
Requires-Dist: pytest ~=5.4 ; extra == "test"
Requires-Dist: pytest-asyncio ~=0.11 ; extra == "test"
Requires-Dist: pytest-cov ~=2.8 ; extra == "test"
Requires-Dist: flake8 ~=3.7 ; extra == "test"
Project-URL: Documentation, https://github.com/ebb29c/asyncio-channel/blob/main/docs/api.md
Provides-Extra: test
